<databaseChangeLog xmlns="http://www.liquibase.org/xml/ns/dbchangelog" xmlns:ext="http://www.liquibase.org/xml/ns/dbchangelog-ext" xmlns:pro="http://www.liquibase.org/xml/ns/pro" xmlns:xsi="http://www.w3.org/2001/XMLSchema-instance" xsi:schemaLocation="http://www.liquibase.org/xml/ns/dbchangelog-ext http://www.liquibase.org/xml/ns/dbchangelog/dbchangelog-ext.xsd http://www.liquibase.org/xml/ns/pro http://www.liquibase.org/xml/ns/pro/liquibase-pro-latest.xsd http://www.liquibase.org/xml/ns/dbchangelog http://www.liquibase.org/xml/ns/dbchangelog/dbchangelog-latest.xsd">
<changeSet author="liquibase" id="1674739169358-20">
        <insert tableName="CODIFICHE">
            <column name="OBJ_ID" valueNumeric="1"/>
            <column name="ID_CODIFICA" value="BARCODE-GS1-128"/>
            <column name="DESCRIZIONE" value="Codifica barcode GS1-128 tot 13"/>
        </insert>
        <insert tableName="CODIFICHE">
            <column name="OBJ_ID" valueNumeric="2"/>
            <column name="ID_CODIFICA" value="QR-CODE"/>
            <column name="DESCRIZIONE" value="QR-CODE CF  11 caratteri"/>
        </insert>
        <insert tableName="CODIFICHE">
            <column name="OBJ_ID" valueNumeric="3"/>
            <column name="ID_CODIFICA" value="BARCODE-128-AIM"/>
            <column name="DESCRIZIONE" value="BARCODE-128-AIM zeri + ccp tot 12"/>
        </insert>
    </changeSet>
    </databaseChangeLog>
